{
  "Focus FS": "2026-06-06",
  "AbbaTek Group Inc": "2026-06-05",
  "Academy Canada": "2026-06-05",
  "ACENET": "2026-06-05",
  "Alt Hotel St John's - Germain Hotels": "2026-06-05",
  "AltoMaxx Technologies Inc": "2026-06-05",
  "Amal Youth & Family Centre": "2026-06-05",
  "Amba Health and Care Canada Limited": "2026-06-05",
  "Angler Solutions Inc.": "2026-06-05",
  "Atlantic Controls a Division of Laurentide Controls": "2026-05-28",
  "Atlantic XL": "2026-06-05",
  "Audyse Technology": "2026-06-05",
  "Avalon Employment": "2026-06-05",
  "Avalon Holographics": "2026-06-05",
  "AXIS Career Services-Association for New Canadians": "2026-06-05",
  "Barrington Consulting": "2026-06-05",
  "BDC": "2026-06-05",
  "BDO Canada LLP": "2026-06-05",
  "Big Land Networks Ltd": "2026-06-05",
  "Bluedrop ISM": "2026-06-05",
  "Bonocle": "2026-06-05",
  "BreatheSuite": "2026-06-05",
  "Breton Group": "2026-06-05",
  "C-CORE": "2026-06-05",
  "Canada-Newfoundland and Labrador Offshore Energy Regulator (C-NLOER)": "2026-06-05",
  "Canadian Global Maritime": "2026-06-05",
  "Canadian Manufacturers & Exporters": "2026-06-05",
  "Carnegie Learning Canada": "2026-06-05",
  "CGI Inc.": "2026-06-05",
  "ChecKin": "2026-06-05",
  "CIBC": "2026-06-05",
  "City of St. John's - Economic Development": "2026-06-06",
  "ClearRisk": "2026-06-06",
  "Cloud North Bookkeeping & Tax": "2026-06-06",
  "CoLab Software": "2026-06-06",
  "College of the North Atlantic": "2026-06-06",
  "Compactica": "2026-06-06",
  "Compusult Limited": "2026-06-06",
  "Copsys Technologies": "2026-06-06",
  "Courtyard by Marriott Hotel St. John's": "2026-06-06",
  "Cox & Palmer": "2026-06-06",
  "Genoa Design International Ltd.": "2026-06-07",
  "Crosbie Salamis Limited": "2026-06-06",
  "CSIpix": "2026-06-06",
  "Deloitte Management Services LP": "2026-06-06",
  "Design By Analysis Engineering Inc.": "2026-06-06",
  "Digital Nova Scotia": "2026-06-06",
  "Digital Six Consulting": "2026-06-06",
  "Dockridge Digital": "2026-06-06",
  "Dovre Group": "2026-06-06",
  "econext": "2026-06-06",
  "eDNAtec Inc.": "2026-06-06",
  "Enaimco": "2026-06-06",
  "Energy NL": "2026-06-06",
  "Energy Research & Innovation Newfoundland & Labrador": "2026-06-06",
  "EPRA-NL": "2026-06-06",
  "Ernst & Young": "2026-06-06",
  "Ethree Online Inc.": "2026-06-06",
  "Export Development Canada": "2026-06-06",
  "Fonemed North America": "2026-06-06",
  "Fortis Inc.": "2026-06-06",
  "Fugro GeoSurveys": "2026-06-07",
  "Genesis": "2026-06-07",
  "Geotexera Inc.": "2026-06-07",
  "Global Affairs Canada": "2026-06-07",
  "Granville Biomedical Inc.": "2026-06-07",
  "GRi Simulations Inc.": "2026-06-07",
  "GroundControl": "2026-06-07",
  "Hampton Inn and Suites By Hilton St. John's Airport": "2026-05-29",
  "Hatch Ltd.": "2026-06-07",
  "Higher Talent Inc.": "2026-06-07",
  "HiTech Communications": "2026-06-07",
  "Ignite Financial Solutions": "2026-06-07",
  "IMP Solutions": "2026-06-07",
  "Innovation, Science & Economic Development Canada": "2026-06-07",
  "Instrumar Limited": "2026-06-07",
  "JAC Digital Marketing Agency": "2026-06-07",
  "KBRS & Meridia Recruitment Solution": "2026-06-07",
  "Keen Payroll & Bookkeeping": "2026-06-07",
  "Killick Capital": "2026-06-07",
  "KPMG LLP": "2026-06-07",
  "Kraken Robotics": "2026-06-07",
  "LadderSpike inc": "2026-06-07",
  "Landmark Surveys & Engineering Limited": "2026-06-07",
  "launch consulting": "2026-06-07",
  "Luxsonic Technologies, Inc.": "2026-06-07",
  "m5 Marketing Communications": "2026-06-07",
  "Marine Atlantic Inc": "2026-06-07",
  "McInnes Cooper": "2026-06-07",
  "Median.co": "2026-06-07",
  "MEDICURO Virtual Health Inc.": "2026-06-07",
  "Memorial University of Newfoundland": "2026-06-07",
  "Milk Moovement": "2026-06-03",
  "Mitacs Inc.": "2026-06-03",
  "MoodBox Inc.": "2026-06-03",
  "Munn Insurance": "2026-06-03",
  "Mysa Smart Thermostat": "2026-06-03",
  "Nasdaq Canada Inc.": "2026-06-03",
  "NavSim Technology Inc.": "2026-06-03",
  "NDITIVE": "2026-06-03",
  "NetBenefit Software Inc": "2026-06-03",
  "Newfoundland Power": "2026-06-03",
  "NLOWE - Newfoundland & Labrador Organization of Women Entrepreneurs": "2026-06-04",
  "NLWIC-College of the North Atlantic": "2026-06-04",
  "North Atlantic": "2026-06-04",
  "Notification API": "2026-06-04",
  "Oceans Advance": "2026-06-04",
  "Office of the Chief Information Officer (OCIO)": "2026-06-04",
  "Omega 365 Canada Inc": "2026-06-04",
  "Osler, Hoskin & Harcourt, LLP": "2026-06-04",
  "PAL Aerospace": "2026-06-04",
  "PARDY'S Waste Management and Industrial Services Limited": "2026-06-04",
  "PELMO International": "2026-06-04",
  "Perfect Day": "2026-06-04",
  "Pinnacle Networks": "2026-06-04",
  "Polyamyna Nanotech Inc": "2026-06-04",
  "PolyUnity Tech Inc.": "2026-06-04",
  "Port of Argentia": "2026-06-04",
  "Prima Information Solutions Inc": "2026-06-04",
  "Propel": "2026-06-04",
  "qualiTEAS Inc.": "2026-06-04",
  "Ray Creative Agency": "2026-06-04",
  "RBCx": "2026-06-04",
  "Repairify": "2026-06-04",
  "Retellio": "2026-06-04",
  "Robot Interactive Marketing": "2026-06-04",
  "Rutter Inc.": "2026-06-04",
  "Seafair": "2026-06-04",
  "SEM Ltd.": "2026-06-04",
  "Sentinel Institute": "2026-06-04",
  "Sequence Bio Inc.": "2026-06-04",
  "SiftMed": "2026-06-04",
  "SmartBin": "2026-06-04",
  "SmartICE Monitoring & Information Inc.": "2026-06-04",
  "Solace Power Inc": "2026-06-04",
  "Sparrow Acoustics Inc": "2026-06-04",
  "Spellbook": "2026-06-04",
  "Springboard Atlantic": "2026-06-04",
  "St. John's Board of Trade": "2026-06-04",
  "Starluv": "2026-06-04",
  "Stewart McKelvey": "2026-06-04",
  "StrobelTEK": "2026-06-05",
  "Strong Data Inc": "2026-06-05",
  "SubC Imaging": "2026-06-05",
  "Supreme Creations INC.": "2026-06-05",
  "TD Commercial Banking": "2026-06-05",
  "Techleft Solutions Inc": "2026-06-05",
  "Telelink": "2026-06-05",
  "The Idea Factory": "2026-06-05",
  "The Newfoundland and Labrador Construction Association": "2026-06-05",
  "Thinkwell Research + Strategy": "2026-06-05",
  "Tiller Engineering Inc.": "2026-06-06",
  "TownSuite Municipal Software": "2026-06-06",
  "Training Works Inc.": "2026-06-06",
  "Triware Technologies Inc.": "2026-06-06",
  "trophi.ai": "2026-06-06",
  "Trudell Medical Limited": "2026-06-06",
  "TxtSquad": "2026-06-06",
  "Venor": "2026-06-06",
  "Veristart": "2026-06-06",
  "Verisult": "2026-06-06",
  "Vifta Technology Limited": "2026-06-07",
  "Virtual Marine Inc.": "2026-06-07",
  "Vish Limited": "2026-06-07",
  "Vision33 Inc.": "2026-06-07",
  "Voronoi Health Analytics Incorporated": "2026-06-07",
  "WaterWerks Agency": "2026-06-07",
  "Wedgwood Insurance Limited": "2026-06-07",
  "Whitecap Scientific Corporation": "2026-06-07",
  "Women in Resource Development Corporation": "2026-06-07",
  "NewSight Technologies Inc.": "2026-06-05"
}